aqeea/__init__.py
aqeea/__main__.py
aqeea/dict.py
aqeea/download.py
aqeea/listing.py
aqeea/read.py
aqeea-0.1b0.dist-info/LICENSE
aqeea-0.1b0.dist-info/METADATA
aqeea-0.1b0.dist-info/WHEEL
aqeea-0.1b0.dist-info/top_level.txt
aqeea-0.1b0.dist-info/RECORD
