Metadata-Version: 2.1
Name: aqeea
Version: 0.1b0
Summary: Access to air quality data from the European Environment Agency.
Home-page: https://github.com/j-m-l-e-u/aqeea_pkg
Author: Jean-Marie Lepioufle
Author-email: Jean-Marie Lepioufle <jm@jeanmarie.eu>
License: MIT + Copyright Jean-Marie Lepioufle
Project-URL: Homepage, https://github.com/j-m-l-e-u/aqeea_pkg
Classifier: Programming Language :: Python :: 3
Requires-Python: >=3.8
License-File: LICENSE
Requires-Dist: requests (==2.28.2)
Requires-Dist: pandas (~=1.5.3)
Requires-Dist: polars (~=0.16.9)
Provides-Extra: example
Requires-Dist: ipython ; extra == 'example'
Requires-Dist: jupyter ; extra == 'example'
Requires-Dist: os ; extra == 'example'
Requires-Dist: osmnx ; extra == 'example'
Provides-Extra: examples
Requires-Dist: ipython ; extra == 'examples'
Requires-Dist: jupyter ; extra == 'examples'
Requires-Dist: os ; extra == 'examples'
Requires-Dist: osmnx ; extra == 'examples'
